pdf2foundry/__init__.py
pdf2foundry/__main__.py
pdf2foundry/docling_env.py
pdf2foundry/py.typed
pdf2foundry/backend/__init__.py
pdf2foundry/backend/caps.py
pdf2foundry/builder/__init__.py
pdf2foundry/builder/ir_builder.py
pdf2foundry/builder/manifest.py
pdf2foundry/builder/packaging.py
pdf2foundry/builder/toc.py
pdf2foundry/builder/toc_template.py
pdf2foundry/cli/__init__.py
pdf2foundry/cli/conversion.py
pdf2foundry/cli/display.py
pdf2foundry/cli/interactive.py
pdf2foundry/cli/main.py
pdf2foundry/cli/parse.py
pdf2foundry/cli/validation.py
pdf2foundry/core/__init__.py
pdf2foundry/core/exceptions.py
pdf2foundry/core/feature_detection.py
pdf2foundry/core/timeout.py
pdf2foundry/ingest/caption_engine.py
pdf2foundry/ingest/caption_html.py
pdf2foundry/ingest/caption_processor.py
pdf2foundry/ingest/content_extractor.py
pdf2foundry/ingest/docling_adapter.py
pdf2foundry/ingest/docling_parser.py
pdf2foundry/ingest/error_handling.py
pdf2foundry/ingest/feature_logger.py
pdf2foundry/ingest/heuristics.py
pdf2foundry/ingest/image_cache.py
pdf2foundry/ingest/ingestion.py
pdf2foundry/ingest/json_io.py
pdf2foundry/ingest/logging_config.py
pdf2foundry/ingest/ocr_engine.py
pdf2foundry/ingest/ocr_processor.py
pdf2foundry/ingest/parallel_processor.py
pdf2foundry/ingest/structured_tables.py
pdf2foundry/ingest/table_processor.py
pdf2foundry/model/content.py
pdf2foundry/model/document.py
pdf2foundry/model/foundry.py
pdf2foundry/model/id_utils.py
pdf2foundry/model/ir.py
pdf2foundry/model/pipeline_options.py
pdf2foundry/models/__init__.py
pdf2foundry/models/registry.py
pdf2foundry/transform/clean_html.py
pdf2foundry/transform/html_wrap.py
pdf2foundry/transform/layout.py
pdf2foundry/transform/links.py
pdf2foundry/transform/reflow.py
pdf2foundry/transform/table_renderer.py
pdf2foundry/ui/progress.py
pdf2foundry-0.1.0a1.dist-info/licenses/LICENSE
pdf2foundry-0.1.0a1.dist-info/METADATA
pdf2foundry-0.1.0a1.dist-info/WHEEL
pdf2foundry-0.1.0a1.dist-info/entry_points.txt
pdf2foundry-0.1.0a1.dist-info/top_level.txt
pdf2foundry-0.1.0a1.dist-info/RECORD
