Metadata-Version: 2.4
Name: pdf2foundry
Version: 0.1.0a1
Summary: Convert born-digital PDFs into Foundry VTT v13 module compendia.
Author-email: Martin Papy <martin.papy@gmail.com>
License:                     GNU GENERAL PUBLIC LICENSE
Project-URL: Homepage, https://github.com/martin-papy/pdf2foundry
Project-URL: Repository, https://github.com/martin-papy/pdf2foundry
Project-URL: Issues, https://github.com/martin-papy/pdf2foundry/issues
Project-URL: Changelog, https://github.com/martin-papy/pdf2foundry/blob/main/RELEASE_NOTES.md
Classifier: Development Status :: 3 - Alpha
Classifier: Intended Audience :: Developers
Classifier: Intended Audience :: End Users/Desktop
Classifier: Operating System :: OS Independent
Classifier: Programming Language :: Python :: 3
Classifier: Programming Language :: Python :: 3.12
Classifier: Topic :: Games/Entertainment :: Role-Playing
Classifier: Topic :: Multimedia :: Graphics :: Graphics Conversion
Classifier: Topic :: Text Processing :: Markup :: HTML
Classifier: Topic :: Utilities
Classifier: Environment :: Console
Classifier: Typing :: Typed
Requires-Python: >=3.12
License-File: LICENSE
Requires-Dist: typer>=0.16.0
Requires-Dist: jinja2>=3.1.6
Requires-Dist: pillow>=11.3.0
Requires-Dist: rich>=14.1.0
Requires-Dist: docling>=2.53.0
Requires-Dist: docling-core>=2.48.1
Requires-Dist: transformers>=4.46.0
Requires-Dist: huggingface_hub>=0.24.2
Requires-Dist: torch>=2.8.0
Requires-Dist: einops>=0.8.0
Requires-Dist: timm>=1.0.0
Requires-Dist: pytesseract>=0.3.13
Provides-Extra: ci-minimal
Requires-Dist: typer>=0.16.0; extra == "ci-minimal"
Requires-Dist: jinja2>=3.1.6; extra == "ci-minimal"
Requires-Dist: pillow>=11.3.0; extra == "ci-minimal"
Requires-Dist: rich>=14.1.0; extra == "ci-minimal"
Requires-Dist: docling>=2.53.0; extra == "ci-minimal"
Requires-Dist: docling-core>=2.48.1; extra == "ci-minimal"
Provides-Extra: dev
Requires-Dist: ruff>=0.13.1; extra == "dev"
Requires-Dist: black>=25.9.0; extra == "dev"
Requires-Dist: mypy>=1.18.2; extra == "dev"
Requires-Dist: pytest>=8.4.2; extra == "dev"
Requires-Dist: pytest-cov>=7.0.0; extra == "dev"
Requires-Dist: pre-commit>=4.3.0; extra == "dev"
Requires-Dist: pytest-xdist>=3.6.1; extra == "dev"
Requires-Dist: pytest-benchmark>=4.0.0; extra == "dev"
Requires-Dist: jsonschema>=4.23.0; extra == "dev"
Requires-Dist: referencing>=0.35.1; extra == "dev"
Requires-Dist: beautifulsoup4>=4.12.3; extra == "dev"
Requires-Dist: lxml>=5.3.0; extra == "dev"
Requires-Dist: reportlab>=4.2.0; extra == "dev"
Requires-Dist: psutil>=6.1.0; extra == "dev"
Requires-Dist: requests>=2.32.0; extra == "dev"
Requires-Dist: tomli>=2.0.0; extra == "dev"
Requires-Dist: tomli-w>=1.0.0; extra == "dev"
Requires-Dist: click>=8.1.0; extra == "dev"
Requires-Dist: python-dotenv>=1.0.0; extra == "dev"
Dynamic: license-file
